hrdagen/__init__.py
hrdagen-0.0.0.dist-info/LICENSE
hrdagen-0.0.0.dist-info/METADATA
hrdagen-0.0.0.dist-info/WHEEL
hrdagen-0.0.0.dist-info/top_level.txt
hrdagen-0.0.0.dist-info/RECORD
