Metadata-Version: 2.1
Name: hrdagen
Version: 0.0.0
Summary: HR and Recruitment data generator
Home-page: UNKNOWN
Author: Nikolay Dudaev
Author-email: nikolay.dudaev@icloud.com
License: MIT
Platform: UNKNOWN
